{
  "persons": [
    {
      "picture": "bag.jpg",
      "name": {"first":"AAA1", "last":"BBB1"},
    },
    {
      "picture": "bicycle.jpg",
      "name": {"first":"AAA2", "last":"BBB2"},
    },
    {
      "picture": "books.jpg",
      "name": {"first":"AAA3", "last":"BBB3"},
    },
    {
      "picture": "car.jpg",
      "name": {"first":"AAA4", "last":"BBB4"},
    },
    {
      "picture": "diamond.jpg",
      "name": {"first":"AAA5", "last":"BBB5"},
    },
    {
      "picture": "dish.jpg",
      "name": {"first":"AAA6", "last":"BBB6"},
    },
    {
      "picture": "dvd.jpg",
      "name": {"first":"AAA7", "last":"BBB7"},
    },
    {
      "picture": "earing.jpeg",
      "name": {"first":"AAA8", "last":"BBB8"},
    },
    {
      "picture": "jeans.jpg",
      "name": {"first":"AAA9", "last":"BBB9"},
    },
    {
      "picture": "shoes.jpg",
      "name": {"first":"AAA10", "last":"BBB10"},
    },
  ]
}